setup.py
src/digimat/__init__.py
src/digimat.n2.egg-info/PKG-INFO
src/digimat.n2.egg-info/SOURCES.txt
src/digimat.n2.egg-info/dependency_links.txt
src/digimat.n2.egg-info/namespace_packages.txt
src/digimat.n2.egg-info/not-zip-safe
src/digimat.n2.egg-info/requires.txt
src/digimat.n2.egg-info/top_level.txt
src/digimat/n2/__init__.py
src/digimat/n2/link.py
src/digimat/n2/n2.py
src/digimat/n2/n29x.py
src/digimat/n2/n2open.py
src/digimat/n2/tuc03.py