Metadata-Version: 1.0
Name: digimat.n2
Version: 0.1.2
Summary: Digimat N2
Home-page: UNKNOWN
Author: Frederic Hess
Author-email: fhess@splust.ch
License: PSF
Platform: UNKNOWN
